{"GeneratedCodeFiles":[],"GeneratedXamlFiles":["C:\\Source\\CriticalInsight\\IdeaBranch\\src\\IdeaBranch.App\\obj\\Debug\\net9.0-windows10.0.19041.0\\win10-x64\\Platforms\\Windows\\App.xaml"],"GeneratedXbfFiles":["C:\\Source\\CriticalInsight\\IdeaBranch\\src\\IdeaBranch.App\\obj\\Debug\\net9.0-windows10.0.19041.0\\win10-x64\\Platforms\\Windows\\App.xbf"],"GeneratedXamlPagesFiles":[],"MSBuildLogEntries":[{"SubCategory":null,"ErrorCode":null,"HelpKeyword":null,"File":null,"LineNumber":0,"ColumnNumber":0,"EndLineNumber":0,"EndColumnNumber":0,"Message":"Xaml Compiler Marker: 12:40:33 PM: 746 perfXC_StartPass2, IdeaBranch.App"},{"SubCategory":null,"ErrorCode":null,"HelpKeyword":null,"File":null,"LineNumber":0,"ColumnNumber":0,"EndLineNumber":0,"EndColumnNumber":0,"Message":"Xaml Compiler Marker: 12:40:33 PM: 762 perfXC_FingerprintCheck, Using managed HashForWinMD"},{"SubCategory":null,"ErrorCode":null,"HelpKeyword":null,"File":null,"LineNumber":0,"ColumnNumber":0,"EndLineNumber":0,"EndColumnNumber":0,"Message":"Xaml Compiler Marker: 12:40:33 PM: 820 perfXC_FingerprintCheck, Using managed HashForWinMD"},{"SubCategory":null,"ErrorCode":null,"HelpKeyword":null,"File":null,"LineNumber":0,"ColumnNumber":0,"EndLineNumber":0,"EndColumnNumber":0,"Message":"Xaml Compiler Marker: 12:40:33 PM: 821 perfXC_FingerprintCheck, Using managed HashForWinMD"},{"SubCategory":null,"ErrorCode":null,"HelpKeyword":null,"File":null,"LineNumber":0,"ColumnNumber":0,"EndLineNumber":0,"EndColumnNumber":0,"Message":"Xaml Compiler Marker: 12:40:33 PM: 824 perfXC_FingerprintCheck, Using managed HashForWinMD"},{"SubCategory":null,"ErrorCode":null,"HelpKeyword":null,"File":null,"LineNumber":0,"ColumnNumber":0,"EndLineNumber":0,"EndColumnNumber":0,"Message":"Xaml Compiler Marker: 12:40:33 PM: 824 perfXC_FingerprintCheck, Using managed HashForWinMD"},{"SubCategory":null,"ErrorCode":null,"HelpKeyword":null,"File":null,"LineNumber":0,"ColumnNumber":0,"EndLineNumber":0,"EndColumnNumber":0,"Message":"Xaml Compiler Marker: 12:40:33 PM: 833 perfXC_RestoredGeneratedPass2CodeFileBackup"},{"SubCategory":null,"ErrorCode":null,"HelpKeyword":null,"File":null,"LineNumber":0,"ColumnNumber":0,"EndLineNumber":0,"EndColumnNumber":0,"Message":"Xaml Compiler Marker: 12:40:33 PM: 838 perfXC_RestoredTypeInfoBackup"}]}